dih/docker_helper.py
dih/gui.py
dih/handler.py
dih/main.py
dih/utils.py
dih-0.0.1.4.dist-info/LICENSE
dih-0.0.1.4.dist-info/METADATA
dih-0.0.1.4.dist-info/WHEEL
dih-0.0.1.4.dist-info/entry_points.txt
dih-0.0.1.4.dist-info/top_level.txt
dih-0.0.1.4.dist-info/RECORD
