Metadata-Version: 2.1
Name: dih
Version: 0.0.1.4
Summary: A tool to save and load the docker image tarball file
Author-email: Max Chang <p513817@gmail.com>
License: MIT License
Project-URL: Homepage, https://github.com/p513817/dih
Project-URL: Issues, https://github.com/p513817/dih/issues
Classifier: Programming Language :: Python :: 3
Classifier: Programming Language :: Python :: 3.8
Classifier: Programming Language :: Python :: 3.10
Classifier: Development Status :: 4 - Beta
Classifier: License :: OSI Approved :: MIT License
Classifier: Operating System :: POSIX :: Linux
Requires-Python: >=3.8
License-File: LICENSE
Requires-Dist: certifi ==2023.11.17
Requires-Dist: charset-normalizer ==3.3.2
Requires-Dist: click ==8.1.7
Requires-Dist: coverage ==7.3.2
Requires-Dist: docker ==7.0.0
Requires-Dist: exceptiongroup ==1.2.0
Requires-Dist: idna ==3.6
Requires-Dist: iniconfig ==2.0.0
Requires-Dist: markdown-it-py ==3.0.0
Requires-Dist: mdurl ==0.1.2
Requires-Dist: packaging ==23.2
Requires-Dist: pluggy ==1.3.0
Requires-Dist: Pygments ==2.17.2
Requires-Dist: pytest ==7.4.3
Requires-Dist: pytest-cov ==4.1.0
Requires-Dist: PyYAML ==6.0.1
Requires-Dist: requests ==2.31.0
Requires-Dist: rich ==13.7.0
Requires-Dist: tomli ==2.0.1
Requires-Dist: urllib3 ==2.1.0
